clapdb/__init__.py
clapdb/client.py
clapdb/dbapi.py
clapdb/exceptions.py
clapdb/sqlalchemy/__init__.py
clapdb/sqlalchemy/datatype.py
clapdb/sqlalchemy/dialect.py
clapdb/superset/__init__.py
clapdb/superset/clapdb.py
clapdb-1.0.0.dist-info/entry_points.txt
clapdb-1.0.0.dist-info/LICENSE
clapdb-1.0.0.dist-info/WHEEL
clapdb-1.0.0.dist-info/METADATA
clapdb-1.0.0.dist-info/RECORD
