Metadata-Version: 2.1
Name: clapdb
Version: 1.0.0
Summary: python client for clapdb
Author-email: "pkgs@stdb.io" <pkgs@stdb.io>
Requires-Python: >=3.11
Classifier: License :: OSI Approved :: MIT License
Classifier: Programming Language :: Python :: 3
Classifier: Development Status :: 4 - Beta
Classifier: Operating System :: OS Independent
Requires-Dist: requests
Project-URL: Bug Tracker, https://github.com/stdbio/clapdb-python-client/issues
Project-URL: Homepage, https://github.com/stdbio/clapdb-python-client
